c64/__init__.py
c64-0.1a0.dist-info/LICENSE
c64-0.1a0.dist-info/METADATA
c64-0.1a0.dist-info/WHEEL
c64-0.1a0.dist-info/top_level.txt
c64-0.1a0.dist-info/RECORD
