Metadata-Version: 2.1
Name: c64
Version: 0.1a0
Summary: Experimental package of ASGI utilities extracted from Datasette
Home-page: https://github.com/simonw/c64
Author: Simon Willison
License: Apache License, Version 2.0
Project-URL: Issues, https://github.com/simonw/c64/issues
Project-URL: CI, https://github.com/simonw/c64/actions
Project-URL: Changelog, https://github.com/simonw/c64/releases
Platform: UNKNOWN
Requires-Python: >=3.6
Provides-Extra: test
Requires-Dist: pytest ; extra == 'test'
Requires-Dist: pytest-asyncio ; extra == 'test'
Requires-Dist: isort ; extra == 'test'
Requires-Dist: black ; extra == 'test'
